.travis.yml
CHANGES.rst
MANIFEST.in
README.rst
setup.py
tox.ini
bundled/libev/Changes
bundled/libev/LICENSE
bundled/libev/Makefile.am
bundled/libev/Makefile.in
bundled/libev/README
bundled/libev/aclocal.m4
bundled/libev/autogen.sh
bundled/libev/config.guess
bundled/libev/config.h.in
bundled/libev/config.sub
bundled/libev/configure
bundled/libev/configure.ac
bundled/libev/depcomp
bundled/libev/ev++.h
bundled/libev/ev.3
bundled/libev/ev.c
bundled/libev/ev.h
bundled/libev/ev.pod
bundled/libev/ev_epoll.c
bundled/libev/ev_kqueue.c
bundled/libev/ev_poll.c
bundled/libev/ev_port.c
bundled/libev/ev_select.c
bundled/libev/ev_vars.h
bundled/libev/ev_win32.c
bundled/libev/ev_wrap.h
bundled/libev/event.c
bundled/libev/event.h
bundled/libev/install-sh
bundled/libev/libev.m4
bundled/libev/ltmain.sh
bundled/libev/missing
bundled/libev/mkinstalldirs
docs/Makefile
docs/source/Async.rst
docs/source/Child.rst
docs/source/Embed.rst
docs/source/Fork.rst
docs/source/Idle.rst
docs/source/Io.rst
docs/source/Loop.rst
docs/source/Periodic.rst
docs/source/Prepare_Check.rst
docs/source/Scheduler.rst
docs/source/Signal.rst
docs/source/Stat.rst
docs/source/Timer.rst
docs/source/Watcher.rst
docs/source/basic_usage.py
docs/source/changes.rst
docs/source/conf.py
docs/source/echo_server.py
docs/source/examples.rst
docs/source/index.rst
docs/source/pyev.rst
docs/source/api/modules.rst
pyev/__init__.py
pyev/tests.py
pyev_static.egg-info/PKG-INFO
pyev_static.egg-info/SOURCES.txt
pyev_static.egg-info/dependency_links.txt
pyev_static.egg-info/top_level.txt
src/Async.c
src/Check.c
src/Child.c
src/Embed.c
src/Fork.c
src/Idle.c
src/Io.c
src/Loop.c
src/Periodic.c
src/PeriodicBase.c
src/Prepare.c
src/Scheduler.c
src/Signal.c
src/Stat.c
src/Timer.c
src/Watcher.c
src/pyev.c
src/pyev.h
utils/__init__.py
utils/bundle.py
utils/detect.py
utils/initlibev.c
utils/msg.py
utils/other.py
utils/vers.c