Metadata-Version: 1.1
Name: pyev-static
Version: 0.9.5
Summary: Python bindings to libev.
Home-page: http://packages.python.org/pyev/
Author: Malek Hadj-Ali
Author-email: lekmalek@gmail.com
License: BSD License / GNU General Public License (GPL)
Platform: Microsoft Windows
Platform: POSIX
Classifier: Development Status :: 4 - Beta
Classifier: Intended Audience :: Developers
Classifier: Intended Audience :: System Administrators
Classifier: License :: OSI Approved :: BSD License
Classifier: License :: OSI Approved :: GNU General Public License (GPL)
Classifier: Operating System :: Microsoft :: Windows :: Windows NT/2000
Classifier: Operating System :: POSIX
Classifier: Programming Language :: Python :: 2.6
Classifier: Programming Language :: Python :: 2.7
Classifier: Programming Language :: Python :: 3.1
Classifier: Programming Language :: Python :: 3.2
